README.md
setup.cfg
setup.py
Kruskals/__init__.py
Kruskals/__main__.py
Kruskals/kruskals.py
Kruskals.egg-info/PKG-INFO
Kruskals.egg-info/SOURCES.txt
Kruskals.egg-info/dependency_links.txt
Kruskals.egg-info/requires.txt
Kruskals.egg-info/top_level.txt