Metadata-Version: 1.2
Name: Kruskals
Version: 1.3.0
Summary: Calculation of Kruskals Distance Measure
Home-page: https://github.com/Rambatino/Kruskals
Author: Mark Ramotowski
Author-email: mark.tint.ramotowski@gmail.com
License: MIT
Keywords: Kruskals pandas numpy scipy statistics statistical analysis
Platform: UNKNOWN
Classifier: Development Status :: 3 - Alpha
Classifier: Intended Audience :: Developers
Classifier: Topic :: Software Development :: Build Tools
Classifier: License :: OSI Approved :: MIT License
Classifier: Programming Language :: Python :: 3.5
Classifier: Programming Language :: Python :: 3.6
Classifier: Programming Language :: Python :: 3.7
Requires-Python: >3.5
